geodatatool/__init__.py
geodatatool/common.py
geodatatool/geodatatool.py
geodatatool/visual.py
geodatatool-0.0.5.dist-info/LICENSE
geodatatool-0.0.5.dist-info/METADATA
geodatatool-0.0.5.dist-info/WHEEL
geodatatool-0.0.5.dist-info/dependency_links.txt
geodatatool-0.0.5.dist-info/top_level.txt
geodatatool-0.0.5.dist-info/RECORD
