Metadata-Version: 2.1
Name: geodatatool
Version: 0.0.5
Summary: Python package for geographic data tools
Home-page: https://github.com/clancygeodata/geodatatool
Author: Clancy Oliver
Author-email: clancy.geodata@gmail.com
License: MIT license
Keywords: geodatatool
Platform: UNKNOWN
Classifier: Development Status :: 2 - Pre-Alpha
Classifier: Intended Audience :: Developers
Classifier: License :: OSI Approved :: MIT License
Classifier: Natural Language :: English
Classifier: Programming Language :: Python :: 3
Classifier: Programming Language :: Python :: 3.5
Classifier: Programming Language :: Python :: 3.6
Classifier: Programming Language :: Python :: 3.7
Classifier: Programming Language :: Python :: 3.8
Requires-Python: >=3.5
Requires-Dist: earthengine-api
Requires-Dist: folium
Requires-Dist: ipyleaflet
Requires-Dist: pillow
Requires-Dist: pyshp
